<?xml version="1.0"?>
<opencv_storage>
<stage3>
  <maxWeakCount>4</maxWeakCount>
  <stageThreshold>-4.6905353665351868e-01</stageThreshold>
  <weakClassifiers>
    <_>
      <internalNodes>
        0 -1 119594 1.0727748740464449e-03</internalNodes>
      <leafValues>
        -8.4444445371627808e-01 6.9090908765792847e-01</leafValues></_>
    <_>
      <internalNodes>
        0 -1 95648 8.2501852884888649e-03</internalNodes>
      <leafValues>
        -6.4659154415130615e-01 7.6039457321166992e-01</leafValues></_>
    <_>
      <internalNodes>
        0 -1 35989 3.2381984055973589e-04</internalNodes>
      <leafValues>
        -7.9174548387527466e-01 5.4930526018142700e-01</leafValues></_>
    <_>
      <internalNodes>
        0 -1 112219 3.2507063588127494e-04</internalNodes>
      <leafValues>
        -1. 4.7267717123031616e-01</leafValues></_></weakClassifiers></stage3>
</opencv_storage>
